jupyter_project/__init__.py
jupyter_project/_version.py
jupyter_project/autoinstance.py
jupyter_project/config.py
jupyter_project/files.py
jupyter_project/handlers.py
jupyter_project/jinja2.py
jupyter_project/project.py
jupyter_project/traits.py
jupyter_project/examples/demo.ipynb
jupyter_project/examples/example.ipynb
jupyter_project/examples/train_model.py
jupyter_project/labextension/jupyter-project-1.0.1.tgz
jupyter_project-1.0.1.data/data/etc/jupyter/jupyter_notebook_config.d/jupyter_project.json
jupyter_project-1.0.1.data/data/share/jupyter/lab/extensions/jupyter-project-1.0.1.tgz
jupyter_project-1.0.1.dist-info/LICENSE
jupyter_project-1.0.1.dist-info/METADATA
jupyter_project-1.0.1.dist-info/WHEEL
jupyter_project-1.0.1.dist-info/top_level.txt
jupyter_project-1.0.1.dist-info/RECORD
