Metadata-Version: 2.1
Name: jupyter-project
Version: 1.0.1
Summary: An JupyterLab extension to handle project and files templates.
Home-page: https://github.com/fcollonval/jupyter-project
Author: Frederic Collonval
License: BSD-3-Clause
Keywords: Jupyter,JupyterLab,template
Platform: Linux
Platform: Mac OS X
Platform: Windows
Classifier: License :: OSI Approved :: BSD License
Classifier: Programming Language :: Python
Classifier: Programming Language :: Python :: 3
Classifier: Programming Language :: Python :: 3.6
Classifier: Programming Language :: Python :: 3.7
Classifier: Programming Language :: Python :: 3.8
Classifier: Framework :: Jupyter
Requires-Dist: cookiecutter
Requires-Dist: jinja2 (~=2.9)
Requires-Dist: jsonschema
Requires-Dist: jupyterlab (~=1.2)
Provides-Extra: all
Requires-Dist: jupyter-conda (~=3.3) ; extra == 'all'
Requires-Dist: jupyterlab-git (<0.20,>=0.10) ; extra == 'all'
Provides-Extra: test
Requires-Dist: pytest ; extra == 'test'
Requires-Dist: pytest-asyncio ; extra == 'test'
